elliptic_curves_fq/__init__.py
elliptic_curves_fq/src/ChinesischerRestsatz.py
elliptic_curves_fq/src/ElGammal.py
elliptic_curves_fq/src/Kurven.py
elliptic_curves_fq/src/Menezes_Vanstone_Kryptosystem.py
elliptic_curves_fq/src/Menezes_vanstone_Ascii.py
elliptic_curves_fq/src/Streamlit.py
elliptic_curves_fq/src/__init__.py
elliptic_curves_fq/src/division_polynomial_fast_curve.py
elliptic_curves_fq/src/elliptischeKurve.py
elliptic_curves_fq/src/endlicheKoerper_Fp.py
elliptic_curves_fq/src/endlicherKoerper_F2n.py
elliptic_curves_fq/src/endlicherKoerper_Fpn.py
elliptic_curves_fq/src/fast_curve.py
elliptic_curves_fq/src/fast_schooftest_multy_process.py
elliptic_curves_fq/src/find_irreducible_polynomial.py
elliptic_curves_fq/src/getrandomcurve.py
elliptic_curves_fq/src/laufzeit.py
elliptic_curves_fq/src/rechen_mit_Fp.py
elliptic_curves_fq/src/rechnen_mit_Fpn.py
elliptic_curves_fq/src/schooftest.py
elliptic_curves_fq/tests/__init__.py
elliptic_curves_fq/tests/test_all.py
elliptic_curves_fq-2.2.1.dist-info/LICENSE
elliptic_curves_fq-2.2.1.dist-info/METADATA
elliptic_curves_fq-2.2.1.dist-info/WHEEL
elliptic_curves_fq-2.2.1.dist-info/top_level.txt
elliptic_curves_fq-2.2.1.dist-info/RECORD
