Metadata-Version: 2.1
Name: elliptic_curves_fq
Version: 2.2.1
Summary: ECC Library
Home-page: https://github.com/HaKa04/package-elliptic-curves-fq
Author: Kaspar Hui
Author-email: <kaspar.hui@gmail.com>
License: MIT
Keywords: python,ECC,Finite Fields
Classifier: Development Status :: 5 - Production/Stable
Classifier: Intended Audience :: Developers
Classifier: Programming Language :: Python :: 3
Classifier: Operating System :: Unix
Classifier: Operating System :: MacOS :: MacOS X
Classifier: Operating System :: Microsoft :: Windows
License-File: LICENSE
